{"containers":[{"CONTAINER_NAME":"MKP DEMAND LIQUIDACION FINAL MAYO 2026 TEC SMARTPHONES","CONTAINER_DEAL_ID":"MLA1633559","ITEMS_EXHIBIDOS":4055,"REAL_OFFER_E":0,"HIGH_ITEMS_E":3071,"MID_ITEMS_E":127,"LOW_ITEMS_E":967,"OFFER_COFINANCED_E":0,"OFFER_SELLER_E":0,"OFFER_PRENEGOTIATED_E":0,"OFFER_COFUNDED_E":0,"OFFER_TIERS_E":0,"OFFER_CUSTOM_E":0,"OFFER_DOD_E":0,"OFFER_SMART_E":0,"OFFER_LIGHTNING_E":0,"OFFER_OTHERS_E":0,"VIEWED_ITEMS":307,"REAL_OFFER_V":0,"HIGH_ITEMS_V":254,"MID_ITEMS_V":22,"LOW_ITEMS_V":31,"NO_OFFER_ITEMS":307,"NO_OFFER_FIN_BY_MELI_E":580,"NO_OFFER_FIN_BY_MELI":43,"NO_OFFER_FIN_BY_MELI_GMV":0,"OFFER_COFINANCED_V":0,"OFFER_SELLER_V":0,"OFFER_PRENEGOTIATED_V":0,"OFFER_COFUNDED_V":0,"OFFER_TIERS_V":0,"OFFER_CUSTOM_V":0,"OFFER_DOD_V":0,"OFFER_SMART_V":0,"OFFER_LIGHTNING_V":0,"OFFER_OTHERS_V":0,"GMV_ITEMS":2,"REAL_OFFER_GMV":0,"HIGH_GMV_ITEMS":2,"MID_GMV_ITEMS":0,"LOW_GMV_ITEMS":0,"NO_OFFER_GMV_ITEMS":2,"OFFER_COFINANCED_GMV":0,"OFFER_SELLER_GMV":0,"OFFER_PRENEGOTIATED_GMV":0,"OFFER_COFUNDED_GMV":0,"OFFER_TIERS_GMV":0,"OFFER_CUSTOM_GMV":0,"OFFER_DOD_GMV":0,"OFFER_SMART_GMV":0,"OFFER_LIGHTNING_GMV":0,"OFFER_OTHERS_GMV":0,"DISCOUNT_POND":0,"UNIQUE_SESSION":23073,"TRANSACTIONS_24HS":100,"TRANSACTIONS_168HS":100,"GMV_LC_24HS_TOTAL":60476778,"GMV_LC_168HS_TOTAL":60476778,"SESSIONS_ITEMS":848},{"CONTAINER_NAME":"MKP DEMAND LIQUIDACION FINAL MAYO 2026 BEAUTY","CONTAINER_DEAL_ID":"MLA1633569","ITEMS_EXHIBIDOS":66689,"REAL_OFFER_E":0,"HIGH_ITEMS_E":64226,"MID_ITEMS_E":425,"LOW_ITEMS_E":3122,"OFFER_COFINANCED_E":0,"OFFER_SELLER_E":0,"OFFER_PRENEGOTIATED_E":0,"OFFER_COFUNDED_E":0,"OFFER_TIERS_E":0,"OFFER_CUSTOM_E":0,"OFFER_DOD_E":0,"OFFER_SMART_E":0,"OFFER_LIGHTNING_E":0,"OFFER_OTHERS_E":0,"VIEWED_ITEMS":374,"REAL_OFFER_V":0,"HIGH_ITEMS_V":348,"MID_ITEMS_V":4,"LOW_ITEMS_V":22,"NO_OFFER_ITEMS":374,"NO_OFFER_FIN_BY_MELI_E":15918,"NO_OFFER_FIN_BY_MELI":122,"NO_OFFER_FIN_BY_MELI_GMV":2,"OFFER_COFINANCED_V":0,"OFFER_SELLER_V":0,"OFFER_PRENEGOTIATED_V":0,"OFFER_COFUNDED_V":0,"OFFER_TIERS_V":0,"OFFER_CUSTOM_V":0,"OFFER_DOD_V":0,"OFFER_SMART_V":0,"OFFER_LIGHTNING_V":0,"OFFER_OTHERS_V":0,"GMV_ITEMS":6,"REAL_OFFER_GMV":0,"HIGH_GMV_ITEMS":6,"MID_GMV_ITEMS":0,"LOW_GMV_ITEMS":0,"NO_OFFER_GMV_ITEMS":6,"OFFER_COFINANCED_GMV":0,"OFFER_SELLER_GMV":0,"OFFER_PRENEGOTIATED_GMV":0,"OFFER_COFUNDED_GMV":0,"OFFER_TIERS_GMV":0,"OFFER_CUSTOM_GMV":0,"OFFER_DOD_GMV":0,"OFFER_SMART_GMV":0,"OFFER_LIGHTNING_GMV":0,"OFFER_OTHERS_GMV":0,"DISCOUNT_POND":0,"UNIQUE_SESSION":30800,"TRANSACTIONS_24HS":221,"TRANSACTIONS_168HS":221,"GMV_LC_24HS_TOTAL":10151767,"GMV_LC_168HS_TOTAL":10151767,"SESSIONS_ITEMS":587},{"CONTAINER_NAME":"MKP DEMAND LIQUIDACION FINAL MAYO 2026 FH MATTRESSES","CONTAINER_DEAL_ID":"MLA1633563","ITEMS_EXHIBIDOS":11115,"REAL_OFFER_E":0,"HIGH_ITEMS_E":10855,"MID_ITEMS_E":72,"LOW_ITEMS_E":563,"OFFER_COFINANCED_E":0,"OFFER_SELLER_E":0,"OFFER_PRENEGOTIATED_E":0,"OFFER_COFUNDED_E":0,"OFFER_TIERS_E":0,"OFFER_CUSTOM_E":0,"OFFER_DOD_E":0,"OFFER_SMART_E":0,"OFFER_LIGHTNING_E":0,"OFFER_OTHERS_E":0,"VIEWED_ITEMS":140,"REAL_OFFER_V":0,"HIGH_ITEMS_V":122,"MID_ITEMS_V":1,"LOW_ITEMS_V":17,"NO_OFFER_ITEMS":140,"NO_OFFER_FIN_BY_MELI_E":6634,"NO_OFFER_FIN_BY_MELI":74,"NO_OFFER_FIN_BY_MELI_GMV":1,"OFFER_COFINANCED_V":0,"OFFER_SELLER_V":0,"OFFER_PRENEGOTIATED_V":0,"OFFER_COFUNDED_V":0,"OFFER_TIERS_V":0,"OFFER_CUSTOM_V":0,"OFFER_DOD_V":0,"OFFER_SMART_V":0,"OFFER_LIGHTNING_V":0,"OFFER_OTHERS_V":0,"GMV_ITEMS":1,"REAL_OFFER_GMV":0,"HIGH_GMV_ITEMS":1,"MID_GMV_ITEMS":0,"LOW_GMV_ITEMS":0,"NO_OFFER_GMV_ITEMS":1,"OFFER_COFINANCED_GMV":0,"OFFER_SELLER_GMV":0,"OFFER_PRENEGOTIATED_GMV":0,"OFFER_COFUNDED_GMV":0,"OFFER_TIERS_GMV":0,"OFFER_CUSTOM_GMV":0,"OFFER_DOD_GMV":0,"OFFER_SMART_GMV":0,"OFFER_LIGHTNING_GMV":0,"OFFER_OTHERS_GMV":0,"DISCOUNT_POND":0,"UNIQUE_SESSION":11893,"TRANSACTIONS_24HS":45,"TRANSACTIONS_168HS":45,"GMV_LC_24HS_TOTAL":23061709,"GMV_LC_168HS_TOTAL":23061709,"SESSIONS_ITEMS":358},{"CONTAINER_NAME":"MKP DEMAND LIQUIDACION FINAL MAYO 2026 FASHION FOOTWEAR","CONTAINER_DEAL_ID":"MLA1633554","ITEMS_EXHIBIDOS":22662,"REAL_OFFER_E":0,"HIGH_ITEMS_E":18466,"MID_ITEMS_E":1027,"LOW_ITEMS_E":3481,"OFFER_COFINANCED_E":0,"OFFER_SELLER_E":0,"OFFER_PRENEGOTIATED_E":0,"OFFER_COFUNDED_E":0,"OFFER_TIERS_E":0,"OFFER_CUSTOM_E":0,"OFFER_DOD_E":0,"OFFER_SMART_E":0,"OFFER_LIGHTNING_E":0,"OFFER_OTHERS_E":0,"VIEWED_ITEMS":1356,"REAL_OFFER_V":0,"HIGH_ITEMS_V":1315,"MID_ITEMS_V":14,"LOW_ITEMS_V":27,"NO_OFFER_ITEMS":1356,"NO_OFFER_FIN_BY_MELI_E":6414,"NO_OFFER_FIN_BY_MELI":442,"NO_OFFER_FIN_BY_MELI_GMV":9,"OFFER_COFINANCED_V":0,"OFFER_SELLER_V":0,"OFFER_PRENEGOTIATED_V":0,"OFFER_COFUNDED_V":0,"OFFER_TIERS_V":0,"OFFER_CUSTOM_V":0,"OFFER_DOD_V":0,"OFFER_SMART_V":0,"OFFER_LIGHTNING_V":0,"OFFER_OTHERS_V":0,"GMV_ITEMS":23,"REAL_OFFER_GMV":0,"HIGH_GMV_ITEMS":22,"MID_GMV_ITEMS":1,"LOW_GMV_ITEMS":0,"NO_OFFER_GMV_ITEMS":23,"OFFER_COFINANCED_GMV":0,"OFFER_SELLER_GMV":0,"OFFER_PRENEGOTIATED_GMV":0,"OFFER_COFUNDED_GMV":0,"OFFER_TIERS_GMV":0,"OFFER_CUSTOM_GMV":0,"OFFER_DOD_GMV":0,"OFFER_SMART_GMV":0,"OFFER_LIGHTNING_GMV":0,"OFFER_OTHERS_GMV":0,"DISCOUNT_POND":0,"UNIQUE_SESSION":63788,"TRANSACTIONS_24HS":772,"TRANSACTIONS_168HS":772,"GMV_LC_24HS_TOTAL":56480491,"GMV_LC_168HS_TOTAL":56480491,"SESSIONS_ITEMS":5704},{"CONTAINER_NAME":"MKP DEMAND LIQUIDACION FINAL MAYO 2026 HEALTH SUPPLEMENTS","CONTAINER_DEAL_ID":"MLA1633585","ITEMS_EXHIBIDOS":9556,"REAL_OFFER_E":0,"HIGH_ITEMS_E":9320,"MID_ITEMS_E":71,"LOW_ITEMS_E":337,"OFFER_COFINANCED_E":0,"OFFER_SELLER_E":0,"OFFER_PRENEGOTIATED_E":0,"OFFER_COFUNDED_E":0,"OFFER_TIERS_E":0,"OFFER_CUSTOM_E":0,"OFFER_DOD_E":0,"OFFER_SMART_E":0,"OFFER_LIGHTNING_E":0,"OFFER_OTHERS_E":0,"VIEWED_ITEMS":88,"REAL_OFFER_V":0,"HIGH_ITEMS_V":87,"MID_ITEMS_V":0,"LOW_ITEMS_V":1,"NO_OFFER_ITEMS":88,"NO_OFFER_FIN_BY_MELI_E":980,"NO_OFFER_FIN_BY_MELI":11,"NO_OFFER_FIN_BY_MELI_GMV":0,"OFFER_COFINANCED_V":0,"OFFER_SELLER_V":0,"OFFER_PRENEGOTIATED_V":0,"OFFER_COFUNDED_V":0,"OFFER_TIERS_V":0,"OFFER_CUSTOM_V":0,"OFFER_DOD_V":0,"OFFER_SMART_V":0,"OFFER_LIGHTNING_V":0,"OFFER_OTHERS_V":0,"GMV_ITEMS":2,"REAL_OFFER_GMV":0,"HIGH_GMV_ITEMS":2,"MID_GMV_ITEMS":0,"LOW_GMV_ITEMS":0,"NO_OFFER_GMV_ITEMS":2,"OFFER_COFINANCED_GMV":0,"OFFER_SELLER_GMV":0,"OFFER_PRENEGOTIATED_GMV":0,"OFFER_COFUNDED_GMV":0,"OFFER_TIERS_GMV":0,"OFFER_CUSTOM_GMV":0,"OFFER_DOD_GMV":0,"OFFER_SMART_GMV":0,"OFFER_LIGHTNING_GMV":0,"OFFER_OTHERS_GMV":0,"DISCOUNT_POND":0,"UNIQUE_SESSION":8233,"TRANSACTIONS_24HS":74,"TRANSACTIONS_168HS":74,"GMV_LC_24HS_TOTAL":3504829,"GMV_LC_168HS_TOTAL":3504829,"SESSIONS_ITEMS":136},{"CONTAINER_NAME":"MKP DEMAND LIQUIDACION FINAL MAYO 2026 HE TELEVISIONS","CONTAINER_DEAL_ID":"MLA1633557","ITEMS_EXHIBIDOS":2536,"REAL_OFFER_E":0,"HIGH_ITEMS_E":1800,"MID_ITEMS_E":46,"LOW_ITEMS_E":872,"OFFER_COFINANCED_E":0,"OFFER_SELLER_E":0,"OFFER_PRENEGOTIATED_E":0,"OFFER_COFUNDED_E":0,"OFFER_TIERS_E":0,"OFFER_CUSTOM_E":0,"OFFER_DOD_E":0,"OFFER_SMART_E":0,"OFFER_LIGHTNING_E":0,"OFFER_OTHERS_E":0,"VIEWED_ITEMS":216,"REAL_OFFER_V":0,"HIGH_ITEMS_V":176,"MID_ITEMS_V":15,"LOW_ITEMS_V":25,"NO_OFFER_ITEMS":216,"NO_OFFER_FIN_BY_MELI_E":1048,"NO_OFFER_FIN_BY_MELI":74,"NO_OFFER_FIN_BY_MELI_GMV":1,"OFFER_COFINANCED_V":0,"OFFER_SELLER_V":0,"OFFER_PRENEGOTIATED_V":0,"OFFER_COFUNDED_V":0,"OFFER_TIERS_V":0,"OFFER_CUSTOM_V":0,"OFFER_DOD_V":0,"OFFER_SMART_V":0,"OFFER_LIGHTNING_V":0,"OFFER_OTHERS_V":0,"GMV_ITEMS":4,"REAL_OFFER_GMV":0,"HIGH_GMV_ITEMS":4,"MID_GMV_ITEMS":0,"LOW_GMV_ITEMS":0,"NO_OFFER_GMV_ITEMS":4,"OFFER_COFINANCED_GMV":0,"OFFER_SELLER_GMV":0,"OFFER_PRENEGOTIATED_GMV":0,"OFFER_COFUNDED_GMV":0,"OFFER_TIERS_GMV":0,"OFFER_CUSTOM_GMV":0,"OFFER_DOD_GMV":0,"OFFER_SMART_GMV":0,"OFFER_LIGHTNING_GMV":0,"OFFER_OTHERS_GMV":0,"DISCOUNT_POND":0,"UNIQUE_SESSION":44694,"TRANSACTIONS_24HS":149,"TRANSACTIONS_168HS":149,"GMV_LC_24HS_TOTAL":93249673,"GMV_LC_168HS_TOTAL":93249673,"SESSIONS_ITEMS":642},{"CONTAINER_NAME":"MKP DEMAND LIQUIDACION FINAL MAYO 2026 HE LARGE APPLIANCES","CONTAINER_DEAL_ID":"MLA1635053","ITEMS_EXHIBIDOS":10784,"REAL_OFFER_E":0,"HIGH_ITEMS_E":9346,"MID_ITEMS_E":108,"LOW_ITEMS_E":1570,"OFFER_COFINANCED_E":0,"OFFER_SELLER_E":0,"OFFER_PRENEGOTIATED_E":0,"OFFER_COFUNDED_E":0,"OFFER_TIERS_E":0,"OFFER_CUSTOM_E":0,"OFFER_DOD_E":0,"OFFER_SMART_E":0,"OFFER_LIGHTNING_E":0,"OFFER_OTHERS_E":0,"VIEWED_ITEMS":143,"REAL_OFFER_V":0,"HIGH_ITEMS_V":135,"MID_ITEMS_V":6,"LOW_ITEMS_V":2,"NO_OFFER_ITEMS":143,"NO_OFFER_FIN_BY_MELI_E":4750,"NO_OFFER_FIN_BY_MELI":56,"NO_OFFER_FIN_BY_MELI_GMV":0,"OFFER_COFINANCED_V":0,"OFFER_SELLER_V":0,"OFFER_PRENEGOTIATED_V":0,"OFFER_COFUNDED_V":0,"OFFER_TIERS_V":0,"OFFER_CUSTOM_V":0,"OFFER_DOD_V":0,"OFFER_SMART_V":0,"OFFER_LIGHTNING_V":0,"OFFER_OTHERS_V":0,"GMV_ITEMS":1,"REAL_OFFER_GMV":0,"HIGH_GMV_ITEMS":1,"MID_GMV_ITEMS":0,"LOW_GMV_ITEMS":0,"NO_OFFER_GMV_ITEMS":1,"OFFER_COFINANCED_GMV":0,"OFFER_SELLER_GMV":0,"OFFER_PRENEGOTIATED_GMV":0,"OFFER_COFUNDED_GMV":0,"OFFER_TIERS_GMV":0,"OFFER_CUSTOM_GMV":0,"OFFER_DOD_GMV":0,"OFFER_SMART_GMV":0,"OFFER_LIGHTNING_GMV":0,"OFFER_OTHERS_GMV":0,"DISCOUNT_POND":0,"UNIQUE_SESSION":5738,"TRANSACTIONS_24HS":26,"TRANSACTIONS_168HS":26,"GMV_LC_24HS_TOTAL":17341770,"GMV_LC_168HS_TOTAL":17341770,"SESSIONS_ITEMS":289},{"CONTAINER_NAME":"MKP DEMAND LIQUIDACION FINAL MAYO 2026 SPORTS GRAL","CONTAINER_DEAL_ID":"MLA1635647","ITEMS_EXHIBIDOS":56103,"REAL_OFFER_E":0,"HIGH_ITEMS_E":53531,"MID_ITEMS_E":578,"LOW_ITEMS_E":3195,"OFFER_COFINANCED_E":0,"OFFER_SELLER_E":0,"OFFER_PRENEGOTIATED_E":0,"OFFER_COFUNDED_E":0,"OFFER_TIERS_E":0,"OFFER_CUSTOM_E":0,"OFFER_DOD_E":0,"OFFER_SMART_E":0,"OFFER_LIGHTNING_E":0,"OFFER_OTHERS_E":0,"VIEWED_ITEMS":100,"REAL_OFFER_V":0,"HIGH_ITEMS_V":92,"MID_ITEMS_V":3,"LOW_ITEMS_V":5,"NO_OFFER_ITEMS":100,"NO_OFFER_FIN_BY_MELI_E":20145,"NO_OFFER_FIN_BY_MELI":29,"NO_OFFER_FIN_BY_MELI_GMV":1,"OFFER_COFINANCED_V":0,"OFFER_SELLER_V":0,"OFFER_PRENEGOTIATED_V":0,"OFFER_COFUNDED_V":0,"OFFER_TIERS_V":0,"OFFER_CUSTOM_V":0,"OFFER_DOD_V":0,"OFFER_SMART_V":0,"OFFER_LIGHTNING_V":0,"OFFER_OTHERS_V":0,"GMV_ITEMS":1,"REAL_OFFER_GMV":0,"HIGH_GMV_ITEMS":1,"MID_GMV_ITEMS":0,"LOW_GMV_ITEMS":0,"NO_OFFER_GMV_ITEMS":1,"OFFER_COFINANCED_GMV":0,"OFFER_SELLER_GMV":0,"OFFER_PRENEGOTIATED_GMV":0,"OFFER_COFUNDED_GMV":0,"OFFER_TIERS_GMV":0,"OFFER_CUSTOM_GMV":0,"OFFER_DOD_GMV":0,"OFFER_SMART_GMV":0,"OFFER_LIGHTNING_GMV":0,"OFFER_OTHERS_GMV":0,"DISCOUNT_POND":0,"UNIQUE_SESSION":4568,"TRANSACTIONS_24HS":15,"TRANSACTIONS_168HS":15,"GMV_LC_24HS_TOTAL":4087450,"GMV_LC_168HS_TOTAL":4087450,"SESSIONS_ITEMS":244},{"CONTAINER_NAME":"MKP DEMAND LIQUIDACION FINAL MAYO 2026 HE CLIMATIZACION","CONTAINER_DEAL_ID":"MLA1635057","ITEMS_EXHIBIDOS":6689,"REAL_OFFER_E":0,"HIGH_ITEMS_E":5830,"MID_ITEMS_E":85,"LOW_ITEMS_E":964,"OFFER_COFINANCED_E":0,"OFFER_SELLER_E":0,"OFFER_PRENEGOTIATED_E":0,"OFFER_COFUNDED_E":0,"OFFER_TIERS_E":0,"OFFER_CUSTOM_E":0,"OFFER_DOD_E":0,"OFFER_SMART_E":0,"OFFER_LIGHTNING_E":0,"OFFER_OTHERS_E":0,"VIEWED_ITEMS":81,"REAL_OFFER_V":0,"HIGH_ITEMS_V":74,"MID_ITEMS_V":3,"LOW_ITEMS_V":4,"NO_OFFER_ITEMS":81,"NO_OFFER_FIN_BY_MELI_E":2931,"NO_OFFER_FIN_BY_MELI":12,"NO_OFFER_FIN_BY_MELI_GMV":2,"OFFER_COFINANCED_V":0,"OFFER_SELLER_V":0,"OFFER_PRENEGOTIATED_V":0,"OFFER_COFUNDED_V":0,"OFFER_TIERS_V":0,"OFFER_CUSTOM_V":0,"OFFER_DOD_V":0,"OFFER_SMART_V":0,"OFFER_LIGHTNING_V":0,"OFFER_OTHERS_V":0,"GMV_ITEMS":2,"REAL_OFFER_GMV":0,"HIGH_GMV_ITEMS":2,"MID_GMV_ITEMS":0,"LOW_GMV_ITEMS":0,"NO_OFFER_GMV_ITEMS":2,"OFFER_COFINANCED_GMV":0,"OFFER_SELLER_GMV":0,"OFFER_PRENEGOTIATED_GMV":0,"OFFER_COFUNDED_GMV":0,"OFFER_TIERS_GMV":0,"OFFER_CUSTOM_GMV":0,"OFFER_DOD_GMV":0,"OFFER_SMART_GMV":0,"OFFER_LIGHTNING_GMV":0,"OFFER_OTHERS_GMV":0,"DISCOUNT_POND":0,"UNIQUE_SESSION":5291,"TRANSACTIONS_24HS":67,"TRANSACTIONS_168HS":67,"GMV_LC_24HS_TOTAL":12634991,"GMV_LC_168HS_TOTAL":12634991,"SESSIONS_ITEMS":137},{"CONTAINER_NAME":"MKP DEMAND LIQUIDACION FINAL MAYO 2026 TEC GAMING","CONTAINER_DEAL_ID":"MLA1633577","ITEMS_EXHIBIDOS":600,"REAL_OFFER_E":0,"HIGH_ITEMS_E":587,"MID_ITEMS_E":6,"LOW_ITEMS_E":17,"OFFER_COFINANCED_E":0,"OFFER_SELLER_E":0,"OFFER_PRENEGOTIATED_E":0,"OFFER_COFUNDED_E":0,"OFFER_TIERS_E":0,"OFFER_CUSTOM_E":0,"OFFER_DOD_E":0,"OFFER_SMART_E":0,"OFFER_LIGHTNING_E":0,"OFFER_OTHERS_E":0,"VIEWED_ITEMS":107,"REAL_OFFER_V":0,"HIGH_ITEMS_V":101,"MID_ITEMS_V":0,"LOW_ITEMS_V":6,"NO_OFFER_ITEMS":107,"NO_OFFER_FIN_BY_MELI_E":152,"NO_OFFER_FIN_BY_MELI":9,"NO_OFFER_FIN_BY_MELI_GMV":0,"OFFER_COFINANCED_V":0,"OFFER_SELLER_V":0,"OFFER_PRENEGOTIATED_V":0,"OFFER_COFUNDED_V":0,"OFFER_TIERS_V":0,"OFFER_CUSTOM_V":0,"OFFER_DOD_V":0,"OFFER_SMART_V":0,"OFFER_LIGHTNING_V":0,"OFFER_OTHERS_V":0,"GMV_ITEMS":0,"REAL_OFFER_GMV":0,"HIGH_GMV_ITEMS":0,"MID_GMV_ITEMS":0,"LOW_GMV_ITEMS":0,"NO_OFFER_GMV_ITEMS":0,"OFFER_COFINANCED_GMV":0,"OFFER_SELLER_GMV":0,"OFFER_PRENEGOTIATED_GMV":0,"OFFER_COFUNDED_GMV":0,"OFFER_TIERS_GMV":0,"OFFER_CUSTOM_GMV":0,"OFFER_DOD_GMV":0,"OFFER_SMART_GMV":0,"OFFER_LIGHTNING_GMV":0,"OFFER_OTHERS_GMV":0,"DISCOUNT_POND":0,"UNIQUE_SESSION":13458,"TRANSACTIONS_24HS":14,"TRANSACTIONS_168HS":14,"GMV_LC_24HS_TOTAL":1069589,"GMV_LC_168HS_TOTAL":1069589,"SESSIONS_ITEMS":249},{"CONTAINER_NAME":"MKP DEMAND LIQUIDACION FINAL MAYO 2026 FASHION APPAREL","CONTAINER_DEAL_ID":"MLA1633572","ITEMS_EXHIBIDOS":12961,"REAL_OFFER_E":0,"HIGH_ITEMS_E":9759,"MID_ITEMS_E":2151,"LOW_ITEMS_E":1144,"OFFER_COFINANCED_E":0,"OFFER_SELLER_E":0,"OFFER_PRENEGOTIATED_E":0,"OFFER_COFUNDED_E":0,"OFFER_TIERS_E":0,"OFFER_CUSTOM_E":0,"OFFER_DOD_E":0,"OFFER_SMART_E":0,"OFFER_LIGHTNING_E":0,"OFFER_OTHERS_E":0,"VIEWED_ITEMS":500,"REAL_OFFER_V":0,"HIGH_ITEMS_V":487,"MID_ITEMS_V":9,"LOW_ITEMS_V":4,"NO_OFFER_ITEMS":500,"NO_OFFER_FIN_BY_MELI_E":3258,"NO_OFFER_FIN_BY_MELI":155,"NO_OFFER_FIN_BY_MELI_GMV":0,"OFFER_COFINANCED_V":0,"OFFER_SELLER_V":0,"OFFER_PRENEGOTIATED_V":0,"OFFER_COFUNDED_V":0,"OFFER_TIERS_V":0,"OFFER_CUSTOM_V":0,"OFFER_DOD_V":0,"OFFER_SMART_V":0,"OFFER_LIGHTNING_V":0,"OFFER_OTHERS_V":0,"GMV_ITEMS":1,"REAL_OFFER_GMV":0,"HIGH_GMV_ITEMS":1,"MID_GMV_ITEMS":0,"LOW_GMV_ITEMS":0,"NO_OFFER_GMV_ITEMS":1,"OFFER_COFINANCED_GMV":0,"OFFER_SELLER_GMV":0,"OFFER_PRENEGOTIATED_GMV":0,"OFFER_COFUNDED_GMV":0,"OFFER_TIERS_GMV":0,"OFFER_CUSTOM_GMV":0,"OFFER_DOD_GMV":0,"OFFER_SMART_GMV":0,"OFFER_LIGHTNING_GMV":0,"OFFER_OTHERS_GMV":0,"DISCOUNT_POND":0,"UNIQUE_SESSION":12271,"TRANSACTIONS_24HS":67,"TRANSACTIONS_168HS":67,"GMV_LC_24HS_TOTAL":4065135,"GMV_LC_168HS_TOTAL":4065135,"SESSIONS_ITEMS":1036},{"CONTAINER_NAME":"MKP DEMAND LIQUIDACION FINAL MAYO 2026 FH FURNITURE","CONTAINER_DEAL_ID":"MLA1635086","ITEMS_EXHIBIDOS":44328,"REAL_OFFER_E":0,"HIGH_ITEMS_E":42458,"MID_ITEMS_E":606,"LOW_ITEMS_E":2465,"OFFER_COFINANCED_E":0,"OFFER_SELLER_E":0,"OFFER_PRENEGOTIATED_E":0,"OFFER_COFUNDED_E":0,"OFFER_TIERS_E":0,"OFFER_CUSTOM_E":0,"OFFER_DOD_E":0,"OFFER_SMART_E":0,"OFFER_LIGHTNING_E":0,"OFFER_OTHERS_E":0,"VIEWED_ITEMS":160,"REAL_OFFER_V":0,"HIGH_ITEMS_V":155,"MID_ITEMS_V":0,"LOW_ITEMS_V":5,"NO_OFFER_ITEMS":160,"NO_OFFER_FIN_BY_MELI_E":16435,"NO_OFFER_FIN_BY_MELI":46,"NO_OFFER_FIN_BY_MELI_GMV":0,"OFFER_COFINANCED_V":0,"OFFER_SELLER_V":0,"OFFER_PRENEGOTIATED_V":0,"OFFER_COFUNDED_V":0,"OFFER_TIERS_V":0,"OFFER_CUSTOM_V":0,"OFFER_DOD_V":0,"OFFER_SMART_V":0,"OFFER_LIGHTNING_V":0,"OFFER_OTHERS_V":0,"GMV_ITEMS":3,"REAL_OFFER_GMV":0,"HIGH_GMV_ITEMS":3,"MID_GMV_ITEMS":0,"LOW_GMV_ITEMS":0,"NO_OFFER_GMV_ITEMS":3,"OFFER_COFINANCED_GMV":0,"OFFER_SELLER_GMV":0,"OFFER_PRENEGOTIATED_GMV":0,"OFFER_COFUNDED_GMV":0,"OFFER_TIERS_GMV":0,"OFFER_CUSTOM_GMV":0,"OFFER_DOD_GMV":0,"OFFER_SMART_GMV":0,"OFFER_LIGHTNING_GMV":0,"OFFER_OTHERS_GMV":0,"DISCOUNT_POND":0,"UNIQUE_SESSION":3790,"TRANSACTIONS_24HS":26,"TRANSACTIONS_168HS":26,"GMV_LC_24HS_TOTAL":2612841,"GMV_LC_168HS_TOTAL":2612841,"SESSIONS_ITEMS":318},{"CONTAINER_NAME":"MKP DEMAND LIQUIDACION FINAL MAYO 2026 CI CONSTRUCCION","CONTAINER_DEAL_ID":"MLA1633583","ITEMS_EXHIBIDOS":42285,"REAL_OFFER_E":0,"HIGH_ITEMS_E":41281,"MID_ITEMS_E":469,"LOW_ITEMS_E":1247,"OFFER_COFINANCED_E":0,"OFFER_SELLER_E":0,"OFFER_PRENEGOTIATED_E":0,"OFFER_COFUNDED_E":0,"OFFER_TIERS_E":0,"OFFER_CUSTOM_E":0,"OFFER_DOD_E":0,"OFFER_SMART_E":0,"OFFER_LIGHTNING_E":0,"OFFER_OTHERS_E":0,"VIEWED_ITEMS":182,"REAL_OFFER_V":0,"HIGH_ITEMS_V":181,"MID_ITEMS_V":0,"LOW_ITEMS_V":1,"NO_OFFER_ITEMS":182,"NO_OFFER_FIN_BY_MELI_E":14700,"NO_OFFER_FIN_BY_MELI":36,"NO_OFFER_FIN_BY_MELI_GMV":0,"OFFER_COFINANCED_V":0,"OFFER_SELLER_V":0,"OFFER_PRENEGOTIATED_V":0,"OFFER_COFUNDED_V":0,"OFFER_TIERS_V":0,"OFFER_CUSTOM_V":0,"OFFER_DOD_V":0,"OFFER_SMART_V":0,"OFFER_LIGHTNING_V":0,"OFFER_OTHERS_V":0,"GMV_ITEMS":1,"REAL_OFFER_GMV":0,"HIGH_GMV_ITEMS":1,"MID_GMV_ITEMS":0,"LOW_GMV_ITEMS":0,"NO_OFFER_GMV_ITEMS":1,"OFFER_COFINANCED_GMV":0,"OFFER_SELLER_GMV":0,"OFFER_PRENEGOTIATED_GMV":0,"OFFER_COFUNDED_GMV":0,"OFFER_TIERS_GMV":0,"OFFER_CUSTOM_GMV":0,"OFFER_DOD_GMV":0,"OFFER_SMART_GMV":0,"OFFER_LIGHTNING_GMV":0,"OFFER_OTHERS_GMV":0,"DISCOUNT_POND":0,"UNIQUE_SESSION":5728,"TRANSACTIONS_24HS":26,"TRANSACTIONS_168HS":26,"GMV_LC_24HS_TOTAL":2140173,"GMV_LC_168HS_TOTAL":2140173,"SESSIONS_ITEMS":374}],"refreshed_at":"2026-05-20T08:05:22"}